yon/client/__init__.py
yon/server/__init__.py
yon/server/_msg.py
yon/server/_rpc.py
yon/server/_transport.py
yon/server/_udp.py
yon/server/_ws.py
yon/server/filters.py
yon-1.1.0.dist-info/license
yon-1.1.0.dist-info/METADATA
yon-1.1.0.dist-info/WHEEL
yon-1.1.0.dist-info/RECORD
